{"CommandType":{"value":8,"Value":"Cmdlet"},"Name":"Add-AzureADMSServicePrincipalDelegatedPermissionClassification","Module":"AzureADPreview","NewCommand":"New-MgServicePrincipalDelegatedPermissionClassification","NewCommandModule":"Microsoft.Graph.Applications","Parameters":{"ServicePrincipalId":{"Name":"ServicePrincipalId","NewName":"ServicePrincipalId","OldType":"System.String","NewType":"System.String","MsgInfo":"","MsgWarning":"","MsgError":""},"PermissionName":{"Name":"PermissionName","NewName":"PermissionName","OldType":"System.String","NewType":"System.String","MsgInfo":"","MsgWarning":"","MsgError":""},"Classification":{"Name":"Classification","NewName":"Classification","OldType":"System.Nullable/Microsoft.Open.MSGraph.Model.DelegatedPermissionClassification+ClassificationEnum","NewType":"System.String","MsgInfo":"","MsgWarning":"","MsgError":""},"PermissionId":{"Name":"PermissionId","NewName":"PermissionId","OldType":"System.String","NewType":"System.String","MsgInfo":"","MsgWarning":"","MsgError":""}},"LinkOldCommand":"https://docs.microsoft.com/en-us/powershell/module/AzureADPreview/Add-AzureADMSServicePrincipalDelegatedPermissionClassification","LinkNewCommand":"https://docs.microsoft.com/en-us/powershell/module/Microsoft.Graph.Applications/New-MgServicePrincipalDelegatedPermissionClassification","LinkExamples":"","LinkApi":"/servicePrincipals/{servicePrincipal-id}/delegatedPermissionClassifications","LinkApiDocs":"","ScopesApplication":"Policy.ReadWrite.PermissionGrant","ScopesDelegate":"Policy.ReadWrite.PermissionGrant","MsgInfo":"","MsgWarning":"","MsgError":"","PSComputerName":"localhost","RunspaceId":"90f8e5cf-1bca-4a80-928b-40e8120598e9","PSShowComputerName":false}
