{"CommandType":{"value":8,"Value":"Cmdlet"},"Name":"Add-AzureADGroupMember","Module":"AzureADPreview","NewCommand":"New-MgGroupMember","NewCommandModule":"Microsoft.Graph.Groups","Parameters":{"RefObjectId":{"Name":"RefObjectId","NewName":"","OldType":"System.String","NewType":"","MsgInfo":"","MsgWarning":"","MsgError":""},"ObjectId":{"Name":"ObjectId","NewName":"","OldType":"System.String","NewType":"","MsgInfo":"","MsgWarning":"","MsgError":""}},"LinkOldCommand":"https://docs.microsoft.com/en-us/powershell/module/AzureADPreview/Add-AzureADGroupMember","LinkNewCommand":"https://docs.microsoft.com/en-us/powershell/module/Microsoft.Graph.Groups/New-MgGroupMember","LinkExamples":"https://github.com/orgs/msgraph/discussions?discussions_q=New-MgGroupMember","LinkApi":null,"LinkApiDocs":"","ScopesApplication":null,"ScopesDelegate":null,"MsgInfo":"","MsgWarning":"","MsgError":"","PSComputerName":"localhost","RunspaceId":"10467a48-3ab2-434a-b4fa-1b2c37137093","PSShowComputerName":false}
