{"CommandType":{"value":8,"Value":"Cmdlet"},"Name":"Get-MsolCompanyInformation","Module":"MSOnline","NewCommand":"Get-MgOrganization","NewCommandModule":"Microsoft.Graph.Identity.DirectoryManagement","Parameters":{"TenantId":{"Name":"TenantId","NewName":"","OldType":"System.Nullable/System.Guid","NewType":"","MsgInfo":"","MsgWarning":"","MsgError":""}},"LinkOldCommand":"https://docs.microsoft.com/en-us/powershell/module/MSOnline/Get-MsolCompanyInformation","LinkNewCommand":"https://docs.microsoft.com/en-us/powershell/module/Microsoft.Graph.Identity.DirectoryManagement/Get-MgOrganization","LinkExamples":"","LinkApi":["/organization","/organization/{organization-id}"],"LinkApiDocs":"","ScopesApplication":["DeviceManagementConfiguration.Read.All","DeviceManagementConfiguration.ReadWrite.All","DeviceManagementServiceConfig.Read.All","DeviceManagementServiceConfig.ReadWrite.All","Directory.Read.All","Directory.ReadWrite.All","Organization.Read.All","Organization.ReadWrite.All"],"ScopesDelegate":["DeviceManagementConfiguration.Read.All","DeviceManagementConfiguration.ReadWrite.All","DeviceManagementServiceConfig.Read.All","DeviceManagementServiceConfig.ReadWrite.All","Directory.Read.All","Directory.ReadWrite.All","Organization.Read.All","Organization.ReadWrite.All","User.Read"],"MsgInfo":"","MsgWarning":"","MsgError":"","PSComputerName":"localhost","RunspaceId":"3ecfdd24-0f4c-4556-a52c-307e6eadf9fc","PSShowComputerName":false}
