{"CommandType":{"value":8,"Value":"Cmdlet"},"Name":"New-AzureADMSNamedLocationPolicy","Module":"AzureADPreview","NewCommand":"New-MgIdentityConditionalAccessNamedLocation","NewCommandModule":"Microsoft.Graph.Identity.SignIns","Parameters":{"IsTrusted":{"Name":"IsTrusted","NewName":"","OldType":"System.Nullable/System.Boolean","NewType":"","MsgInfo":"","MsgWarning":"","MsgError":""},"IpRanges":{"Name":"IpRanges","NewName":"","OldType":"System.Collections.Generic.List/Microsoft.Open.MSGraph.Model.IpRange","NewType":"","MsgInfo":"","MsgWarning":"","MsgError":""},"OdataType":{"Name":"OdataType","NewName":"","OldType":"System.String","NewType":"","MsgInfo":"","MsgWarning":"","MsgError":""},"DisplayName":{"Name":"DisplayName","NewName":"DisplayName","OldType":"System.String","NewType":"System.String","MsgInfo":"","MsgWarning":"","MsgError":""},"Id":{"Name":"Id","NewName":"Id","OldType":"System.String","NewType":"System.String","MsgInfo":"","MsgWarning":"","MsgError":""},"IncludeUnknownCountriesAndRegions":{"Name":"IncludeUnknownCountriesAndRegions","NewName":"","OldType":"System.Nullable/System.Boolean","NewType":"","MsgInfo":"","MsgWarning":"","MsgError":""},"CountriesAndRegions":{"Name":"CountriesAndRegions","NewName":"","OldType":"System.Collections.Generic.List/Microsoft.Open.MSGraph.Model.CountriesAndRegion","NewType":"","MsgInfo":"","MsgWarning":"","MsgError":""}},"LinkOldCommand":"https://docs.microsoft.com/en-us/powershell/module/AzureAD/New-AzureADMSNamedLocationPolicy?view=azureadps-2.0-preview","LinkNewCommand":"https://docs.microsoft.com/en-us/powershell/module/Microsoft.Graph.Identity.SignIns/New-MgIdentityConditionalAccessNamedLocation","LinkExamples":"https://github.com/orgs/msgraph/discussions?discussions_q=New-MgIdentityConditionalAccessNamedLocation","LinkApi":"/identity/conditionalAccess/namedLocations","LinkApiDocs":"","ScopesApplication":["Policy.Read.All","Policy.ReadWrite.ConditionalAccess"],"ScopesDelegate":["Policy.Read.All","Policy.ReadWrite.ConditionalAccess"],"MsgInfo":"","MsgWarning":"","MsgError":"","PSComputerName":"localhost","RunspaceId":"7f0dba66-fa92-4330-8068-58e035d3c005","PSShowComputerName":false}
